MicrosoftKeyizhiKezhixingwenjianHeTongyongMubiaoWenjiangeshiWenjianGuifan/README.md
MicrosoftKeyizhiKezhixingwenjianHeTongyongMubiaoWenjiangeshiWenjianGuifan/__init__.py
MicrosoftKeyizhiKezhixingwenjianHeTongyongMubiaoWenjiangeshiWenjianGuifan/__main__.py
MicrosoftKeyizhiKezhixingwenjianHeTongyongMubiaoWenjiangeshiWenjianGuifan/file.pdf
MicrosoftKeyizhiKezhixingwenjianHeTongyongMubiaoWenjiangeshiWenjianGuifan/index.html
microsoft_keyizhi_kezhixingwenjian_he_tongyong_mubiao_wenjiangeshi_wenjian_guifan-2024.3.2.0.dist-info/METADATA
microsoft_keyizhi_kezhixingwenjian_he_tongyong_mubiao_wenjiangeshi_wenjian_guifan-2024.3.2.0.dist-info/WHEEL
microsoft_keyizhi_kezhixingwenjian_he_tongyong_mubiao_wenjiangeshi_wenjian_guifan-2024.3.2.0.dist-info/entry_points.txt
microsoft_keyizhi_kezhixingwenjian_he_tongyong_mubiao_wenjiangeshi_wenjian_guifan-2024.3.2.0.dist-info/top_level.txt
microsoft_keyizhi_kezhixingwenjian_he_tongyong_mubiao_wenjiangeshi_wenjian_guifan-2024.3.2.0.dist-info/RECORD
